kv_platform_sdk/__init__.py
kv_platform_sdk/async_client.py
kv_platform_sdk/sync_client.py
kv_platform_sdk/_http/__init__.py
kv_platform_sdk/_http/_async.py
kv_platform_sdk/_http/base.py
kv_platform_sdk/_http/sync.py
kv_platform_sdk/models/__init__.py
kv_platform_sdk/models/comparison.py
kv_platform_sdk/models/documents.py
kv_platform_sdk/models/extractor.py
kv_platform_sdk/models/form_filler.py
kv_platform_sdk/models/generation.py
kv_platform_sdk/models/model_data.py
kv_platform_sdk/models/questionnaire_filler.py
kv_platform_sdk/models/search_and_inference.py
kv_platform_sdk/resources/comparison.py
kv_platform_sdk/resources/data_extractor.py
kv_platform_sdk/resources/documents.py
kv_platform_sdk/resources/faq_generator.py
kv_platform_sdk/resources/form_filler.py
kv_platform_sdk/resources/generate_draft.py
kv_platform_sdk/resources/k_search.py
kv_platform_sdk/resources/questionnarie_filler.py
kv_platform_sdk/resources/text_summarizer.py
kv_platform_sdk/resources/timeline_builder.py
kv_platform-0.1.1.dist-info/METADATA
kv_platform-0.1.1.dist-info/WHEEL
kv_platform-0.1.1.dist-info/top_level.txt
kv_platform-0.1.1.dist-info/RECORD
