Metadata-Version: 2.4
Name: kv-platform
Version: 0.1.1
Summary: Python SDK for k-v.ai platform
Requires-Python: >=3.10
Requires-Dist: httpx>=0.25
Requires-Dist: pydantic>=2.0
